swats/__init__.py
swats/optim.py
pytorch_swats-0.1.0.dist-info/LICENSE
pytorch_swats-0.1.0.dist-info/METADATA
pytorch_swats-0.1.0.dist-info/WHEEL
pytorch_swats-0.1.0.dist-info/top_level.txt
pytorch_swats-0.1.0.dist-info/RECORD
