Metadata-Version: 2.1
Name: pytorch-swats
Version: 0.1.0
Summary: PyTorch implementation of SWATS algorithm.
Home-page: https://github.com/Mrpatekful/swats
Author: Patrik Purgai
Author-email: purgai.patrik@gmail.com
License: UNKNOWN
Platform: UNKNOWN
Classifier: Programming Language :: Python :: 3
Classifier: License :: OSI Approved :: MIT License
Classifier: Operating System :: OS Independent
Requires-Dist: torch
